switch_api/__init__.py
switch_api/initialize.py
switch_api/_authentication/__init__.py
switch_api/_authentication/_authentication.py
switch_api/_authentication/_credentials_store/__init__.py
switch_api/_authentication/_credentials_store/_credentials_store.py
switch_api/_authentication/_msal/__init__.py
switch_api/_authentication/_msal/_custom_application.py
switch_api/_compute/__init__.py
switch_api/_compute/_commands.py
switch_api/_compute/_compute.py
switch_api/_compute/_iotservice.py
switch_api/_compute/_models.py
switch_api/_compute/_utils.py
switch_api/_guide/__init__.py
switch_api/_guide/main.py
switch_api/_guide/processor.py
switch_api/_utils/__init__.py
switch_api/_utils/_constants.py
switch_api/_utils/_marketplace.py
switch_api/_utils/_platform.py
switch_api/_utils/_utils.py
switch_api/analytics/__init__.py
switch_api/analytics/analytics.py
switch_api/cache/__init__.py
switch_api/cache/cache.py
switch_api/controls/__init__.py
switch_api/controls/_constants.py
switch_api/controls/_enums.py
switch_api/controls/_mqtt.py
switch_api/controls/controls.py
switch_api/dataset/__init__.py
switch_api/dataset/dataset.py
switch_api/email/__init__.py
switch_api/email/email_sender.py
switch_api/error_handlers/__init__.py
switch_api/error_handlers/error_handlers.py
switch_api/extensions/__init__.py
switch_api/extensions/extensions.py
switch_api/extensions/field_meta.py
switch_api/extensions/helpers.py
switch_api/extensions/pipeline.py
switch_api/integration/__init__.py
switch_api/integration/_utils.py
switch_api/integration/helpers.py
switch_api/integration/integration.py
switch_api/pipeline/__init__.py
switch_api/pipeline/automation.py
switch_api/pipeline/definitions.py
switch_api/pipeline/pipeline.py
switch_api/platform_insights/__init__.py
switch_api/platform_insights/platform_insights.py
switch_api-0.6.10.dist-info/AUTHORS.rst
switch_api-0.6.10.dist-info/LICENCE
switch_api-0.6.10.dist-info/METADATA
switch_api-0.6.10.dist-info/WHEEL
switch_api-0.6.10.dist-info/top_level.txt
switch_api-0.6.10.dist-info/RECORD
