Metadata-Version: 2.1
Name: switch-api
Version: 0.6.10
Summary: A complete package for data ingestion into the Switch Automation Platform.
Home-page: UNKNOWN
Author: Switch Automation Pty Ltd.
License: MIT License
Platform: UNKNOWN
Classifier: Development Status :: 2 - Pre-Alpha
Classifier: License :: OSI Approved :: MIT License
Classifier: Intended Audience :: Other Audience
Classifier: Programming Language :: Python :: 3
Classifier: Programming Language :: Python :: 3.8
Classifier: Programming Language :: Python :: 3.9
Classifier: Natural Language :: English
Requires-Python: >=3.8.0
License-File: LICENCE
License-File: AUTHORS.rst
Requires-Dist: pandas==1.5.3
Requires-Dist: requests
Requires-Dist: azure-storage-blob
Requires-Dist: pandera[io]==0.7.1
Requires-Dist: azure-servicebus
Requires-Dist: msal>=1.11.0
Requires-Dist: paho-mqtt==1.6.1
Requires-Dist: uvicorn==0.22.0
Requires-Dist: fastapi==0.98.0
Requires-Dist: pyodbc==4.0.39
Requires-Dist: cachetools==5.5.0
Requires-Dist: numexpr==2.10.2
